pymath/__init__.py
pymath/__main__.py
pymath/counting.py
pymath/other.py
pymath/number_theory/__init__.py
pymath/number_theory/factor.py
pymath/number_theory/number_types.py
pymath/number_theory/primes.py
pymath2-6.1.3.data/scripts/pymath
pymath2-6.1.3.dist-info/LICENSE.txt
pymath2-6.1.3.dist-info/METADATA
pymath2-6.1.3.dist-info/WHEEL
pymath2-6.1.3.dist-info/top_level.txt
pymath2-6.1.3.dist-info/RECORD
