Metadata-Version: 2.1
Name: pymath2
Version: 6.1.3
Summary: Easy calculations on the command line with Python
Home-page: https://github.com/cjbassi/pymath
Author: Caleb Bassi
Author-email: UNKNOWN
License: MIT
Platform: UNKNOWN
Requires-Dist: matplotlib
Requires-Dist: numpy
